<annotation>
	<folder>dogs2</folder>
	<filename>dog.2569.jpg</filename>
	<path>C:\Users\dan09\Downloads\annotations_images-main\annotations_images-main\annotation_images_dan\dogs2\dog.2569.jpg</path>
	<source>
		<database>Unknown</database>
	</source>
	<size>
		<width>307</width>
		<height>383</height>
		<depth>3</depth>
	</size>
	<segmented>0</segmented>
	<object>
		<name>dog</name>
		<pose>Unspecified</pose>
		<truncated>0</truncated>
		<difficult>0</difficult>
		<bndbox>
			<xmin>80</xmin>
			<ymin>12</ymin>
			<xmax>252</xmax>
			<ymax>199</ymax>
		</bndbox>
	</object>
</annotation>
