<annotation>
	<folder>dogs2</folder>
	<filename>dog.2284.jpg</filename>
	<path>C:\Users\dan09\Downloads\annotations_images-main\annotations_images-main\annotation_images_dan\dogs2\dog.2284.jpg</path>
	<source>
		<database>Unknown</database>
	</source>
	<size>
		<width>400</width>
		<height>395</height>
		<depth>3</depth>
	</size>
	<segmented>0</segmented>
	<object>
		<name>dog</name>
		<pose>Unspecified</pose>
		<truncated>0</truncated>
		<difficult>0</difficult>
		<bndbox>
			<xmin>127</xmin>
			<ymin>40</ymin>
			<xmax>285</xmax>
			<ymax>212</ymax>
		</bndbox>
	</object>
</annotation>
